frictionless_dfour/__init__.py
frictionless_dfour/__main__.py
frictionless_dfour/config.py
frictionless_dfour/dfour.py
frictionless_dfour/assets/VERSION
frictionless_dfour/program/__init__.py
frictionless_dfour/program/common.py
frictionless_dfour/program/main.py
frictionless_dfour/program/workspace.py
frictionless_dfour-0.1.0b11.dist-info/LICENSE.md
frictionless_dfour-0.1.0b11.dist-info/METADATA
frictionless_dfour-0.1.0b11.dist-info/WHEEL
frictionless_dfour-0.1.0b11.dist-info/entry_points.txt
frictionless_dfour-0.1.0b11.dist-info/top_level.txt
frictionless_dfour-0.1.0b11.dist-info/RECORD
