Metadata-Version: 2.1
Name: frictionless-dfour
Version: 0.1.0b11
Summary: Dfour Storage for frictionless-py
Home-page: https://github.com/cividi/frictionless-dfour
Author: Thorben Westerhuys
Author-email: thorben@cividi.ch
License: MIT
Keywords: data validation,frictionless data,open data,json schema,json table schema,data package,tabular data package
Platform: UNKNOWN
Classifier: Development Status :: 4 - Beta
Classifier: Environment :: Console
Classifier: Intended Audience :: Developers
Classifier: License :: OSI Approved :: MIT License
Classifier: Operating System :: OS Independent
Classifier: Programming Language :: Python :: 3
Classifier: Programming Language :: Python :: 3.6
Classifier: Programming Language :: Python :: 3.7
Classifier: Programming Language :: Python :: 3.8
Classifier: Topic :: Software Development :: Libraries :: Python Modules
Requires-Dist: gql
Requires-Dist: frictionless
Requires-Dist: dictdiffer
Requires-Dist: tzlocal (==2.1)
Provides-Extra: dev
Requires-Dist: mypy ; extra == 'dev'
Requires-Dist: moto ; extra == 'dev'
Requires-Dist: black ; extra == 'dev'
Requires-Dist: jinja2 ; extra == 'dev'
Requires-Dist: pylama ; extra == 'dev'
Requires-Dist: pytest ; extra == 'dev'
Requires-Dist: ipython ; extra == 'dev'
Requires-Dist: pymysql ; extra == 'dev'
Requires-Dist: livemark ; extra == 'dev'
Requires-Dist: psycopg2 ; extra == 'dev'
Requires-Dist: pytest-cov ; extra == 'dev'
Requires-Dist: pytest-vcr ; extra == 'dev'
Requires-Dist: pytest-only ; extra == 'dev'
Requires-Dist: oauth2client ; extra == 'dev'
Requires-Dist: requests-mock ; extra == 'dev'
Requires-Dist: python-dotenv ; extra == 'dev'
Requires-Dist: pydoc-markdown ; extra == 'dev'
Requires-Dist: docstring-parser ; extra == 'dev'
